spacemakerlog/__init__.py
spacemakerlog/log.py
spacemakerlog-0.2.8.dist-info/METADATA
spacemakerlog-0.2.8.dist-info/RECORD
spacemakerlog-0.2.8.dist-info/WHEEL
spacemakerlog-0.2.8.dist-info/top_level.txt
