Metadata-Version: 2.1
Name: spacemakerlog
Version: 0.2.8
Summary: Structured logging for Spacemaker AI
Home-page: https://github.com/spacemakerai/spacemaker-logging/tree/master/python
Author: Spacemaker AI
Author-email: developers@spacemaker.ai
License: MIT
Platform: UNKNOWN
Requires-Dist: logging
Requires-Dist: structlog
Requires-Dist: python-json-logger
